squares/__init__.py
squares/_version.py
squares/squares.py
squares_rng-1.0.0.dist-info/LICENSE
squares_rng-1.0.0.dist-info/METADATA
squares_rng-1.0.0.dist-info/WHEEL
squares_rng-1.0.0.dist-info/top_level.txt
squares_rng-1.0.0.dist-info/RECORD
