Metadata-Version: 2.1
Name: squares-rng
Version: 1.0.0
Summary: A simple counter-based pseudo random number generator implementation based on arXiv:2004.06278
Home-page: https://github.com/Oafish1/Squares
Author: Oafish1
License: GNLv3
Platform: UNKNOWN
Classifier: License :: OSI Approved :: GNU General Public License v3 (GPLv3)
Classifier: Programming Language :: Python :: 3
Classifier: Programming Language :: Python :: 3.7
Classifier: Programming Language :: Python :: 3.8
Classifier: Programming Language :: Python :: 3.9
